orangic/__init__.py
orangic/client.py
orangic/py.typed
orangic-0.1.0.dist-info/licenses/LICENSE
orangic-0.1.0.dist-info/METADATA
orangic-0.1.0.dist-info/WHEEL
orangic-0.1.0.dist-info/top_level.txt
orangic-0.1.0.dist-info/RECORD
