Metadata-Version: 2.4
Name: orangic
Version: 0.1.0
Summary: The official Python library for the Orangic API (Pre-release)
Home-page: https://github.com/erhan1209/orangic-python
Author: Orangic
Author-email: Orangic <support@orangic.tech>
License: MIT
Project-URL: Homepage, https://orangic.tech
Project-URL: Documentation, https://orangic.tech/docs
Project-URL: Repository, https://github.com/erhan1209/orangic-python
Keywords: orangic,api,ai,machine learning,llm
Classifier: Development Status :: 2 - Pre-Alpha
Classifier: Intended Audience :: Developers
Classifier: License :: OSI Approved :: MIT License
Classifier: Programming Language :: Python :: 3
Classifier: Programming Language :: Python :: 3.8
Classifier: Programming Language :: Python :: 3.9
Classifier: Programming Language :: Python :: 3.10
Classifier: Programming Language :: Python :: 3.11
Classifier: Programming Language :: Python :: 3.12
Requires-Python: >=3.8
License-File: LICENSE
Requires-Dist: httpx>=0.24.0
Dynamic: author
Dynamic: home-page
Dynamic: license-file
Dynamic: requires-python
